{"name":"Landing Page 2","layout":[{"groupname":"","settings":{"background":{"image":{"position":"center","repeat":"tile","attachment":"scroll"}},"padding":{"top":0,"left":0,"right":0,"bottom":0},"border":{"top":{"width":0,"style":"none","radius":0},"left":{"width":0,"style":"none","radius":0},"right":{"width":0,"style":"none","radius":0},"bottom":{"width":0,"style":"none","radius":0}},"margin":{"top":0,"left":0,"right":0,"bottom":0}},"rows":[{"type":"one","columns":{"col1":{"widgets":[{"id":"wpzoom-wysiwyg-16","class":"WPZOOM_Wyswig","settings":{"title":"","text":"<h1 style=\"text-align: center;\">\u00a0Build Your Website Today!<\/h1><h4 style=\"text-align: center;\"><em>Everything you need to build your website quickly and professionally!<\/em><\/h4>","type":"visual"}},{"id":"wpzoom-wysiwyg-17","class":"WPZOOM_Wyswig","settings":{"title":"","text":"<img src=\"http:\/\/www.wpzoom.com\/images\/builder_assets\/browser-builder.png\" width=\"595\" height=\"437\" class=\"aligncenter\" \/>","type":"html"}}]}}}]},{"groupname":"","settings":{"background":{"image":{"position":"center","repeat":"tile","attachment":"scroll"}},"padding":{"top":0,"left":0,"right":0,"bottom":0},"border":{"top":{"width":0,"style":"none","radius":0},"left":{"width":0,"style":"none","radius":0},"right":{"width":0,"style":"none","radius":0},"bottom":{"width":0,"style":"none","radius":0}},"margin":{"top":0,"left":0,"right":0,"bottom":0}},"rows":[{"type":"one","columns":{"col1":{"widgets":[{"id":"wpzoom-call-to-action-20","class":"WPZOOM_Widget_Call_To_Action","settings":{"title":"","separator":"or","caption_align":"center","description":"","button_text":"Sign up Today","button_url":"http:\/\/www.wpzoom.com\/","button_txtcolor":"","button_bgcolor":"#52cc5a","button_2_text":"View Features","button_2_url":"http:\/\/www.wpzoom.com\/builder\/","button_2_txtcolor":"#333333","button_2_bgcolor":"#e1dee7","button_skin":"two-btn"}}]}}}]},{"groupname":"","settings":{"background":{"image":{"position":"center","repeat":"tile","attachment":"scroll"}},"padding":{"top":0,"left":0,"right":0,"bottom":0},"border":{"top":{"width":0,"style":"none","radius":0},"left":{"width":0,"style":"none","radius":0},"right":{"width":0,"style":"none","radius":0},"bottom":{"width":0,"style":"none","radius":0}},"margin":{"top":0,"left":0,"right":0,"bottom":0}},"rows":[{"type":"one","columns":{"col1":{"widgets":[{"id":"wpzoom-call-to-action-21","class":"WPZOOM_Widget_Call_To_Action","settings":{"title":"Unique Features","separator":"or","caption_align":"center","description":"","button_text":"","button_url":"","button_txtcolor":"","button_bgcolor":"","button_2_text":"","button_2_url":"","button_2_txtcolor":"","button_2_bgcolor":"","button_skin":"btn-right"}}]}}},{"type":"three","columns":{"col1":{"width":34.6,"widgets":[{"id":"wpzoom-feature-box-20","class":"WPZOOM_Feature_Box","settings":{"title":"Media Slider","description":"Curabitur blandit tempus porttitor. Maecenas sed diam eget risus varius blandit sit amet non magna.","caption_align":"center","selected-tab":"icon","icon-name":"fa fa-picture-o","img-icon":0,"img-icon-size":"medium","img-icon-align":"none","background":"#276cdc","color":"#ffffff","roundness":"100px","width":"139px","icon-size":"52px"}}]},"col2":{"width":32.8,"widgets":[{"id":"wpzoom-feature-box-21","class":"WPZOOM_Feature_Box","settings":{"title":"Call to Action","description":"Curabitur blandit tempus porttitor. Maecenas sed diam eget risus varius blandit sit amet non magna.","caption_align":"center","selected-tab":"icon","icon-name":"fa fa-bullhorn","img-icon":0,"img-icon-size":"medium","img-icon-align":"none","background":"#276cdc","color":"#ffffff","roundness":"100px","width":"139px","icon-size":"52px"}}]},"col3":{"width":32.6,"widgets":[{"id":"wpzoom-feature-box-22","class":"WPZOOM_Feature_Box","settings":{"title":"Contact Form","description":"Curabitur blandit tempus porttitor. Maecenas sed diam eget risus varius blandit sit amet non magna.","caption_align":"center","selected-tab":"icon","icon-name":"fa fa-pencil-square-o","img-icon":0,"img-icon-size":"medium","img-icon-align":"none","background":"#276cdc","color":"#ffffff","roundness":"100px","width":"139px","icon-size":"52px"}}]}}},{"type":"three","columns":{"col1":{"width":34.6,"widgets":[{"id":"wpzoom-feature-box-23","class":"WPZOOM_Feature_Box","settings":{"title":"Pricing Tables","description":"Curabitur blandit tempus porttitor. Maecenas sed diam eget risus varius blandit sit amet non magna.","caption_align":"center","selected-tab":"icon","icon-name":"fa fa-usd","img-icon":0,"img-icon-size":"medium","img-icon-align":"none","background":"#276cdc","color":"#ffffff","roundness":"100px","width":"139px","icon-size":"52px"}}]},"col2":{"width":32.8,"widgets":[{"id":"wpzoom-feature-box-24","class":"WPZOOM_Feature_Box","settings":{"title":"WYSIWYG","description":"Curabitur blandit tempus porttitor. Maecenas sed diam eget risus varius blandit sit amet non magna.","caption_align":"center","selected-tab":"icon","icon-name":"fa fa-font","img-icon":0,"img-icon-size":"medium","img-icon-align":"none","background":"#276cdc","color":"#ffffff","roundness":"100px","width":"139px","icon-size":"52px"}}]},"col3":{"width":32.6,"widgets":[{"id":"wpzoom-feature-box-25","class":"WPZOOM_Feature_Box","settings":{"title":"Testimonials","description":"Curabitur blandit tempus porttitor. Maecenas sed diam eget risus varius blandit sit amet non magna.","caption_align":"center","selected-tab":"icon","icon-name":"fa fa-quote-left","img-icon":0,"img-icon-size":"medium","img-icon-align":"none","background":"#276cdc","color":"#ffffff","roundness":"100px","width":"139px","icon-size":"52px"}}]}}},{"type":"one","columns":{"col1":{"widgets":[{"id":"wpzoom-call-to-action-22","class":"WPZOOM_Widget_Call_To_Action","settings":{"title":"","separator":"or","caption_align":"center","description":"<a href=\"http:\/\/www.wpzoom.com\/builder\" target=\"_blank\">View all Features<\/a>","button_text":"","button_url":"","button_txtcolor":"","button_bgcolor":"","button_2_text":"","button_2_url":"","button_2_txtcolor":"","button_2_bgcolor":"","button_skin":"btn-right"}}]}}}]},{"groupname":"","settings":{"background":{"color":"#f7f7f7","image":{"position":"center","repeat":"tile","attachment":"scroll"}},"padding":{"top":0,"left":15,"right":15,"bottom":0},"border":{"top":{"width":0,"style":"none","radius":0},"left":{"width":0,"style":"none","radius":0},"right":{"width":0,"style":"none","radius":0},"bottom":{"width":0,"style":"none","radius":0}},"margin":{"top":0,"left":0,"right":0,"bottom":0}},"rows":[{"type":"one","columns":{"col1":{"widgets":[{"id":"wpzoom-call-to-action-23","class":"WPZOOM_Widget_Call_To_Action","settings":{"title":"Loved by customers around the world!","separator":"or","caption_align":"center","description":"","button_text":"","button_url":"","button_txtcolor":"","button_bgcolor":"","button_2_text":"","button_2_url":"","button_2_txtcolor":"","button_2_bgcolor":"","button_skin":"btn-right"}}]}}},{"type":"one","columns":{"col1":{"widgets":[{"id":"wpzoom-testimonials-6","class":"WPZlb_Testimonials","settings":{"title":"","show_photo":"on","show_author":"on","show_author_position":"on","show_author_company":"on","show_author_company_link":"on","item_num":2,"random_post":"on"}}]}}},{"type":"one","columns":{"col1":{"widgets":[{"id":"wpzoom-clients-4","class":"WPZlb_Clients","settings":{"title":"","show_count":"4","random":"on"}}]}}}]},{"groupname":"","settings":{"background":{"image":{"position":"center","repeat":"tile","attachment":"scroll"}},"padding":{"top":0,"left":0,"right":0,"bottom":0},"border":{"top":{"width":0,"style":"none","radius":0},"left":{"width":0,"style":"none","radius":0},"right":{"width":0,"style":"none","radius":0},"bottom":{"width":0,"style":"none","radius":0}},"margin":{"top":0,"left":0,"right":0,"bottom":0}},"rows":[{"type":"one","columns":{"col1":{"widgets":[{"id":"wpzoom-call-to-action-24","class":"WPZOOM_Widget_Call_To_Action","settings":{"title":"Screenshots","separator":"or","caption_align":"center","description":"","button_text":"","button_url":"","button_txtcolor":"","button_bgcolor":"#52cc5a","button_2_text":"","button_2_url":"","button_2_txtcolor":"","button_2_bgcolor":"","button_skin":"centered"}},{"id":"wpzoom-media-slider-8","class":"WPZOOM_Widget_Media_Slider","settings":{"title":"","slideshow_post":3861,"show_title":false,"autoplay":false,"autoplay_interval":4000,"thumbs_width":150,"thumbs_height":120,"slide_effect":0,"nav_position":"bottom","slide_skin":"carousel","caption_position":"right","caption_position_full":"bottom","caption_align":"left","nav_type":"-1"}}]}}},{"type":"divider"}]},{"groupname":"","settings":{"background":{"image":{"position":"center","repeat":"tile","attachment":"scroll"}},"padding":{"top":0,"left":0,"right":0,"bottom":0},"border":{"top":{"width":0,"style":"none","radius":0},"left":{"width":0,"style":"none","radius":0},"right":{"width":0,"style":"none","radius":0},"bottom":{"width":0,"style":"none","radius":0}},"margin":{"top":0,"left":0,"right":0,"bottom":0}},"rows":[{"type":"one","columns":{"col1":{"widgets":[{"id":"wpzoom-call-to-action-25","class":"WPZOOM_Widget_Call_To_Action","settings":{"title":"Get the right plan for your needs!","separator":"or","caption_align":"center","description":"","button_text":"","button_url":"","button_txtcolor":"","button_bgcolor":"","button_2_text":"","button_2_url":"","button_2_txtcolor":"","button_2_bgcolor":"","button_skin":"btn-right"}}]}}},{"type":"one","columns":{"col1":{"widgets":[{"id":"wpzoom-pricing-table-2","class":"WPZOOM_Widget_Pricing_Table","settings":{"title":"","plans":[{"planname":"Personal","plancolor":"#52cc5a","price":"$39","pricetitle":"Lifetime Updates","features":"1 Site License\r\n1 Year of Support\r\nAccess to all Features\r\nUnlimited Layouts","button":"Join Now","buttonurl":"#"},{"planname":"Business","plancolor":"#0087d4","price":"$99","pricetitle":"Lifetime Updates","features":"5 Sites License\r\n1 Year of Support\r\nAccess to all Features\r\nUnlimited Layouts","button":"Join Now","buttonurl":"#"},{"planname":"Agency","plancolor":"#111111","price":"$149","pricetitle":"Lifetime Updates","features":"20 Sites License\r\n1 Year of Support\r\nAccess to all Features\r\nUnlimited Layouts","button":"Join Now","buttonurl":"#"}]}}]}}}]}]}